outlook_meetings/__init__.py
outlook_meetings/__main__.py
outlook_meetings/cli.py
outlook_meetings/outlookmeet.py
outlook_meetings-0.0.1.dist-info/licenses/LICENSE
outlook_meetings-0.0.1.dist-info/METADATA
outlook_meetings-0.0.1.dist-info/WHEEL
outlook_meetings-0.0.1.dist-info/entry_points.txt
outlook_meetings-0.0.1.dist-info/top_level.txt
outlook_meetings-0.0.1.dist-info/RECORD
