Metadata-Version: 2.4
Name: outlook-meetings
Version: 0.0.1
Summary: Create outlook meetings using cli
Author: Sukhbinder Singh
License: Apache-2.0
Project-URL: Homepage, https://github.com/sukhbinder/outlook-meetings
Project-URL: Changelog, https://github.com/sukhbinder/outlook-meetings/releases
Project-URL: Issues, https://github.com/sukhbinder/outlook-meetings/issues
Project-URL: CI, https://github.com/sukhbinder/outlook-meetings/actions
Classifier: License :: OSI Approved :: Apache Software License
Requires-Python: >3.10
License-File: LICENSE
Requires-Dist: pywin32
Requires-Dist: dateutils
Provides-Extra: test
Requires-Dist: pytest; extra == "test"
Dynamic: license-file
